ingestion_game/__init__.py
ingestion_game/main.py
ingestion_game/requirements.txt
ingestion_game/application/__init__.py
ingestion_game/application/get_output.py
ingestion_game/application/logic_ingestion.py
ingestion_game/application/read_file.py
ingestion_game/application/read_hierarchy.py
ingestion_game/application/read_important_keys.py
ingestion_game/domain/__init__.py
ingestion_game/domain/rules.py
ingestion_game-0.1.3.dist-info/METADATA
ingestion_game-0.1.3.dist-info/WHEEL
ingestion_game-0.1.3.dist-info/entry_points.txt
ingestion_game-0.1.3.dist-info/licenses/LICENSE
ingestion_game-0.1.3.dist-info/RECORD
