Metadata-Version: 2.1
Name: ingestion_game
Version: 0.1.3
Summary: The ingestion game CLI
Author-email: Txema Bermudez <txema.bermudez@gmail.com>
License-Expression: GPL-3.0-or-later
License-File: LICENSE
Classifier: Development Status :: 4 - Beta
Classifier: Environment :: Console
Classifier: License :: OSI Approved :: GNU General Public License v3 (GPLv3)
Classifier: Programming Language :: Python :: 3.11
Requires-Python: >=3.11
Requires-Dist: click==8.1.7
Requires-Dist: pydantic==2.4.2
